carton/__init__.py
carton/cart.py
carton/models.py
carton/module_loading.py
carton/settings.py
carton/templatetags/__init__.py
carton/templatetags/carton_tags.py
carton/tests/__init__.py
carton/tests/models.py
carton/tests/settings.py
carton/tests/tests.py
carton/tests/urls.py
carton/tests/views.py
py3_django_enriched_carton-0.1.0.dist-info/LICENSE
py3_django_enriched_carton-0.1.0.dist-info/METADATA
py3_django_enriched_carton-0.1.0.dist-info/WHEEL
py3_django_enriched_carton-0.1.0.dist-info/top_level.txt
py3_django_enriched_carton-0.1.0.dist-info/RECORD
