Metadata-Version: 2.1
Name: py3-django-enriched-carton
Version: 0.1.0
Summary: django-enriched-carton is a simple and lightweight application for shopping carts and wish lists. Forked of django-carton. Python3 and Django 3.2LTS are supported. 
Home-page: https://github.com/knyazz/py3-django-enriched-carton
Author: smirnov.ev
Author-email: knyazz@gmail.com
License: UNKNOWN
Platform: UNKNOWN
Classifier: Programming Language :: Python
Classifier: License :: OSI Approved :: MIT License
Classifier: Operating System :: OS Independent
Classifier: Topic :: Software Development :: Libraries :: Python Modules
Classifier: Intended Audience :: Developers
Classifier: Development Status :: 4 - Beta
License-File: LICENSE
Requires-Dist: Django (>=3.2.0)
